dpmmlearn/__init__.py
dpmmlearn/__version__.py
dpmmlearn/density.py
dpmmlearn/dpmm.py
dpmmlearn/probability.py
dpmmlearn/utils.py
dpmmlearn-0.0.1b1.dist-info/LICENSE
dpmmlearn-0.0.1b1.dist-info/LICENSE-3RD-PARTY
dpmmlearn-0.0.1b1.dist-info/METADATA
dpmmlearn-0.0.1b1.dist-info/WHEEL
dpmmlearn-0.0.1b1.dist-info/top_level.txt
dpmmlearn-0.0.1b1.dist-info/RECORD
