Metadata-Version: 2.1
Name: dpmmlearn
Version: 0.0.1b1
Summary: Dirichlet process mixture model in Python with scikit-learn like API.
Home-page: https://github.com/ground0state/dpmmlearn
Author: Masafumi Abeta
Author-email: ground0state@gmail.com
License: MIT
Platform: UNKNOWN
Classifier: Development Status :: 3 - Alpha
Classifier: License :: OSI Approved :: MIT License
Classifier: Intended Audience :: Developers
Classifier: Intended Audience :: Science/Research
Classifier: Topic :: Software Development
Classifier: Topic :: Scientific/Engineering
Classifier: Programming Language :: Python
Classifier: Programming Language :: Python :: 3
Requires-Python: >=3.7
License-File: LICENSE
License-File: LICENSE-3RD-PARTY
Requires-Dist: numpy
Requires-Dist: scipy
Requires-Dist: scikit-learn
